textalytics_aws/aws_entity_recognition.py
textalytics_azure/azure_entity_recognition.py
textalytics_gcp/gcp_entity_recognition.py
textalytics_hosted/textalytics_entity_recognition.py
textalytics_cloud_api_adapters-0.1.4.dist-info/entry_points.txt
textalytics_cloud_api_adapters-0.1.4.dist-info/WHEEL
textalytics_cloud_api_adapters-0.1.4.dist-info/METADATA
textalytics_cloud_api_adapters-0.1.4.dist-info/RECORD
